MANIFEST.in
README.rst
TODO
pavement.py
paver-minilib.zip
requirements.txt
setup.py
pysimavrgui/__init__.py
pysimavrgui/buttongame.py
pysimavrgui/compgame.py
pysimavrgui/font.bmp
pysimavrgui/infogame.py
pysimavrgui/lcdgame.py
pysimavrgui/ledgame.py
pysimavrgui/ledrowgame.py
pysimavrgui/maingame.py
pysimavrgui/sgm7game.py
pysimavrgui/spkgame.py
pysimavrgui/textgame.py
pysimavrgui.egg-info/PKG-INFO
pysimavrgui.egg-info/SOURCES.txt
pysimavrgui.egg-info/dependency_links.txt
pysimavrgui.egg-info/not-zip-safe
pysimavrgui.egg-info/requires.txt
pysimavrgui.egg-info/top_level.txt
pysimavrgui/examples/__init__.py
pysimavrgui/examples/arduino/__init__.py
pysimavrgui/examples/arduino/lcd.pde
pysimavrgui/examples/arduino/led.pde
pysimavrgui/examples/arduino/print.pde
pysimavrgui/examples/gui/__init__.py
pysimavrgui/examples/gui/buttongame_ex.py
pysimavrgui/examples/gui/lcdgame_ex.py
pysimavrgui/examples/gui/ledgame_ex.py
pysimavrgui/examples/gui/ledrowgame_ex.py
pysimavrgui/examples/gui/sgm7game_ex.py
pysimavrgui/examples/gui/spkgame_ex.py
pysimavrgui/examples/gui/textgame_ex.py
pysimavrgui/examples/sim/__init__.py
pysimavrgui/examples/sim/arduino.py
pysimavrgui/examples/sim/avrsimmain.py
pysimavrgui/examples/sim/lcd.elf
pysimavrgui/examples/sim/lcd.py
pysimavrgui/examples/sim/ledramp.elf
pysimavrgui/examples/sim/ledramp.py
pysimavrgui/examples/sim/sgm7.elf
pysimavrgui/examples/sim/sgm7.py
pysimavrgui/examples/sim/spk.elf
pysimavrgui/examples/sim/spk.py
pysimavrgui/examples/sim/udp.py