Metadata-Version: 1.0
Name: pysimavrgui
Version: 0.0.3
Summary: Simple GUI elements for AVR and arduino simulation.
Home-page: https://github.com/ponty/pysimavrgui
Author: ponty
Author-email: UNKNOWN
License: BSD
Keywords: simavr
Platform: UNKNOWN
Classifier: License :: OSI Approved :: BSD License
Classifier: Natural Language :: English
Classifier: Operating System :: OS Independent
Classifier: Programming Language :: Python
